graph_it/__init__.py
pandadasher-0.0.1.dist-info/LICENSE
pandadasher-0.0.1.dist-info/METADATA
pandadasher-0.0.1.dist-info/WHEEL
pandadasher-0.0.1.dist-info/top_level.txt
pandadasher-0.0.1.dist-info/RECORD
