Metadata-Version: 2.1
Name: pandadasher
Version: 0.0.1
Summary: pandadasher is a lib of my pandas dependent dash functions 
Home-page: https://github.com/Phillyclause89/PandaDasher
Author: Philip "Phillyclause89" Alexander-Lees
Author-email: palexan1@comcast.net
License: MIT
Platform: UNKNOWN
